shiba/__init__.py
shiba/codepoint_tokenizer.py
shiba/local_self_attention.py
shiba/local_transformer_encoder_layer.py
shiba/model.py
shiba/multi_hashing_embedder.py
shiba/position_embedder.py
shiba_model-0.1.1.dist-info/LICENSE.md
shiba_model-0.1.1.dist-info/METADATA
shiba_model-0.1.1.dist-info/WHEEL
shiba_model-0.1.1.dist-info/top_level.txt
shiba_model-0.1.1.dist-info/RECORD
