Metadata-Version: 2.1
Name: shiba-model
Version: 0.1.1
Summary: An efficient character-level transformer encoder, pretrained for Japanese
Home-page: https://github.com/octanove/shiba
Author: Octanove Labs
Author-email: mindful.jt@gmail.com
Keywords: natural language processing,deep learning,transformer
Classifier: Programming Language :: Python :: 3
Classifier: License :: OSI Approved :: Apache Software License
Classifier: Operating System :: OS Independent
Requires-Python: >=3.6
License-File: LICENSE.md
Requires-Dist: torch
Requires-Dist: local-attention (==1.4.1)
